saePy/__init__.py
saePy/eblupBHF.py
saePy/eblupFH.py
saePy/eblupSFH.py
saePy/mseFH.py
saePy/mseSFH.py
saePy/pbmseBHF.py
saepy-0.2.0.dist-info/licenses/LICENSE
saepy-0.2.0.dist-info/METADATA
saepy-0.2.0.dist-info/WHEEL
saepy-0.2.0.dist-info/top_level.txt
saepy-0.2.0.dist-info/RECORD
