Metadata-Version: 2.4
Name: saePy
Version: 0.2.0
Summary: Small Area Estimation Python package
Author: Agus Riyanto
Requires-Python: >=3.8
License-File: LICENSE
Requires-Dist: numpy
Requires-Dist: scipy
Requires-Dist: polars
Requires-Dist: patsy
Dynamic: license-file
Dynamic: requires-python
